phbdl/__init__.py
phbdl/main.py
phbdl-0.1.7.dist-info/LICENSE
phbdl-0.1.7.dist-info/METADATA
phbdl-0.1.7.dist-info/WHEEL
phbdl-0.1.7.dist-info/entry_points.txt
phbdl-0.1.7.dist-info/top_level.txt
phbdl-0.1.7.dist-info/zip-safe
phbdl-0.1.7.dist-info/RECORD
