Metadata-Version: 2.1
Name: phbdl
Version: 0.1.7
Summary: a tiny and smart cli video downloader for pxxxhub
Home-page: https://github.com/yontonl/phbdl
Author: sunbless
Author-email: sunblessliu@gmail.com
License: MIT
Keywords: video downloader
Platform: UNKNOWN
Requires-Dist: requests
Requires-Dist: js2py
Requires-Dist: bs4
